libfaketime/__init__.py
libfaketime/_version.py
libfaketime/vendor/libfaketime/COPYING
libfaketime/vendor/libfaketime/Makefile
libfaketime/vendor/libfaketime/src/Makefile
libfaketime/vendor/libfaketime/src/Makefile.OSX
libfaketime/vendor/libfaketime/src/faketime.c
libfaketime/vendor/libfaketime/src/faketime_common.h
libfaketime/vendor/libfaketime/src/libfaketime.c
libfaketime/vendor/libfaketime/src/libfaketime.map
libfaketime/vendor/libfaketime/src/libfaketime.so.1
libfaketime/vendor/libfaketime/src/sunos_endian.h
libfaketime/vendor/libfaketime/src/time_ops.h
libfaketime/vendor/libfaketime/src/uthash.h
libfaketime-3.0.0.dist-info/LICENSE
libfaketime-3.0.0.dist-info/METADATA
libfaketime-3.0.0.dist-info/WHEEL
libfaketime-3.0.0.dist-info/entry_points.txt
libfaketime-3.0.0.dist-info/top_level.txt
libfaketime-3.0.0.dist-info/RECORD
