Metadata-Version: 2.1
Name: libfaketime
Version: 3.0.0
Summary: A fast alternative to freezegun that wraps libfaketime.
Home-page: http://pypi.python.org/pypi/libfaketime/
Author: Simon Weber
Author-email: simon@simonmweber.com
License: GPLv2
Classifier: License :: OSI Approved :: GNU General Public License v2 (GPLv2)
Classifier: Development Status :: 5 - Production/Stable
Classifier: Intended Audience :: Developers
Classifier: Operating System :: OS Independent
Classifier: Programming Language :: Python
Classifier: Programming Language :: Python :: 3.9
Classifier: Programming Language :: Python :: 3.10
Classifier: Programming Language :: Python :: 3.11
Classifier: Programming Language :: Python :: 3.12
Classifier: Programming Language :: Python :: 3.13
Classifier: Programming Language :: Python :: Implementation :: CPython
Classifier: Programming Language :: Python :: Implementation :: PyPy
Classifier: Topic :: Software Development :: Libraries :: Python Modules
License-File: LICENSE
Requires-Dist: python-dateutil >=1.3
Requires-Dist: pytz
